crawlers/__init__.py
orioncrawlers_pkg_rioatmadja2018-0.1.1585018212.dist-info/METADATA
orioncrawlers_pkg_rioatmadja2018-0.1.1585018212.dist-info/WHEEL
orioncrawlers_pkg_rioatmadja2018-0.1.1585018212.dist-info/top_level.txt
orioncrawlers_pkg_rioatmadja2018-0.1.1585018212.dist-info/zip-safe
orioncrawlers_pkg_rioatmadja2018-0.1.1585018212.dist-info/RECORD
