Metadata-Version: 2.1
Name: orioncrawlers-pkg-rioatmadja2018
Version: 0.1.1585018212
Summary: Engines to collect data.
Home-page: UNKNOWN
Author: Rio Atmadja
Author-email: rioatmadja2018@gmail.com
License: UNKNOWN
Platform: UNKNOWN
Classifier: Programming Language :: Python :: 3
Classifier: Operating System :: OS Independent
Classifier: Intended Audience :: Developers
Requires-Python: >=3.6
Requires-Dist: phantomjs (==1.1.4)
Requires-Dist: selenium (==3.141.0)
Requires-Dist: urllib3 (==1.25.8)
